21.fpga-cpu-hdmi-alu/register_file.v
`default_nettype none

/*
 * MiniISA register file.
 *
 * - 32 registers of 32 bits, of which R0 is hardwired to zero.
 * - Two combinational read ports for Ra and Rb.
 * - One synchronous write port for Rd.
 * - One registered read-only debug port.
 *
 * R0 IS HARDWIRED TO ZERO: writes are dropped, reads always return zero. It is
 * a rule of the ISA, not of this implementation, so this file is byte for byte
 * the same in every MiniCPU folder. See 1.isa/isa.md section 1.
 *
 * The write port is the only place that knows about R0. The read path is
 * deliberately untouched: reset clears all 32 entries and nothing ever writes
 * entry 0, so `registers[0]` is zero by construction and yosys propagates it as
 * a constant, removing the flops and the mux input on its own. An explicit
 * `(addr == 0) ? 0 : ...` would add a mux to the combinational read path, which
 * is the critical path this design has spent effort keeping short: it is what
 * forced STATE_DECODE to exist. See timing.md.
 */
module register_file (
    input clk,
    input reset,

    input [4:0] read_address_a,
    output [31:0] read_data_a,
    input [4:0] read_address_b,
    output [31:0] read_data_b,

    input write_enable,
    input [4:0] write_address,
    input [31:0] write_data,

    input [4:0] debug_address,
    output reg [31:0] debug_data
);

  reg [31:0] registers[0:31];
  integer index;

  /*
   * Debug is intentionally two cycles deep: first capture the requested
   * address, then capture the selected register. UART debug traffic tolerates
   * this latency and the large 32-to-1 mux no longer ends at a distant monitor
   * register. The CPU read ports remain combinational. See timing.md.
   */
  reg [4:0] debug_address_registered;

  assign read_data_a = registers[read_address_a];
  assign read_data_b = registers[read_address_b];
  always @(posedge clk) begin
    if (reset) begin
      debug_address_registered <= 5'd0;
      debug_data <= 32'h0000_0000;

      for (index = 0; index < 32; index = index + 1) begin
        registers[index] <= 32'h0000_0000;
      end
    end else begin
      debug_address_registered <= debug_address;
      debug_data <= registers[debug_address_registered];

      if (write_enable && write_address != 5'd0) begin
        registers[write_address] <= write_data;
      end
    end
  end
endmodule

`default_nettype wire

6.fpga-cpu/register_file_tb.v
`timescale 1ns / 1ps
`default_nettype none

module register_file_tb;

  reg clk = 1'b0;
  reg reset = 1'b1;
  reg [4:0] read_address_a = 5'd0;
  reg [4:0] read_address_b = 5'd0;
  reg write_enable = 1'b0;
  reg [4:0] write_address = 5'd0;
  reg [31:0] write_data = 32'h0000_0000;
  reg [4:0] debug_address = 5'd0;

  wire [31:0] read_data_a;
  wire [31:0] read_data_b;
  wire [31:0] debug_data;

  integer index;

  always #5 clk = ~clk;

  register_file dut (
      .clk(clk),
      .reset(reset),
      .read_address_a(read_address_a),
      .read_data_a(read_data_a),
      .read_address_b(read_address_b),
      .read_data_b(read_data_b),
      .write_enable(write_enable),
      .write_address(write_address),
      .write_data(write_data),
      .debug_address(debug_address),
      .debug_data(debug_data)
  );

  task write_register;
    input [4:0] address;
    input [31:0] data;
    begin
      @(negedge clk);
      write_address = address;
      write_data = data;
      write_enable = 1'b1;
      @(negedge clk);
      write_enable = 1'b0;
    end
  endtask

  task expect_debug_register;
    input [4:0] address;
    input [31:0] expected;
    begin
      @(negedge clk);
      debug_address = address;
      repeat (2) @(posedge clk);
      #1;

      if (debug_data !== expected) begin
        $fatal(1, "Debug R%0d mismatch", address);
      end
    end
  endtask

  initial begin
    $dumpvars(0, register_file_tb);

    repeat (2) @(negedge clk);
    reset = 1'b0;

    // Reset must clear every register, including R0.
    for (index = 0; index < 32; index = index + 1) begin
      expect_debug_register(index, 32'h0000_0000);
    end

    // The two CPU read ports operate independently and simultaneously.
    write_register(5'd1, 32'h1234_5678);
    write_register(5'd2, 32'hdead_beef);
    read_address_a = 5'd1;
    read_address_b = 5'd2;
    #1;
    if (read_data_a !== 32'h1234_5678) $fatal(1, "Read port A mismatch");
    if (read_data_b !== 32'hdead_beef) $fatal(1, "Read port B mismatch");

    /*
     * R0 esta cableado a cero: la escritura se descarta y la lectura sigue
     * valiendo cero. Ver 1.isa/isa.md seccion 1.
     *
     * El banco no tiene ninguna logica de lectura para R0, a proposito: como
     * el reset lo puso a cero y nadie lo escribe, vale cero por construccion.
     * Por eso este caso tiene que ir DESPUES de una escritura de verdad --las
     * de R1 y R2, arriba--: si el puerto de escritura estuviera roto del todo,
     * un R0 a cero no demostraria nada por si solo.
     */
    write_register(5'd0, 32'hffff_ffff);
    read_address_a = 5'd0;
    #1;
    if (read_data_a !== 32'h0000_0000) $fatal(1, "R0 acepto una escritura");
    // Y la escritura descartada no se cuela en el vecino.
    read_address_a = 5'd1;
    #1;
    if (read_data_a !== 32'h1234_5678) $fatal(1, "la escritura a R0 toco R1");

    // The debug port can inspect a register independently of the CPU ports.
    expect_debug_register(5'd2, 32'hdead_beef);

    // Data and address changes must have no effect while writes are disabled.
    @(negedge clk);
    write_enable = 1'b0;
    write_address = 5'd1;
    write_data = 32'haaaa_5555;
    @(negedge clk);
    expect_debug_register(5'd1, 32'h1234_5678);

    $display("PASS: register file behavior is correct");
    $finish;
  end
endmodule

`default_nettype wire

6.fpga-cpu/dump.vcd
$date
	Sun Sep 13 23:21:55 2026
$end
$version
	Icarus Verilog
$end
$timescale
	1ps
$end
$scope module register_file_tb $end
$var wire 32 ! read_data_b [31:0] $end
$var wire 32 " read_data_a [31:0] $end
$var wire 32 # debug_data [31:0] $end
$var reg 1 $ clk $end
$var reg 5 % debug_address [4:0] $end
$var reg 5 & read_address_a [4:0] $end
$var reg 5 ' read_address_b [4:0] $end
$var reg 1 ( reset $end
$var reg 5 ) write_address [4:0] $end
$var reg 32 * write_data [31:0] $end
$var reg 1 + write_enable $end
$var integer 32 , index [31:0] $end
$scope module dut $end
$var wire 1 $ clk $end
$var wire 5 - debug_address [4:0] $end
$var wire 5 . read_address_a [4:0] $end
$var wire 5 / read_address_b [4:0] $end
$var wire 32 0 read_data_a [31:0] $end
$var wire 32 1 read_data_b [31:0] $end
$var wire 1 ( reset $end
$var wire 5 2 write_address [4:0] $end
$var wire 32 3 write_data [31:0] $end
$var wire 1 + write_enable $end
$var reg 5 4 debug_address_registered [4:0] $end
$var reg 32 5 debug_data [31:0] $end
$var integer 32 6 index [31:0] $end
$upscope $end
$scope task expect_debug_register $end
$var reg 5 7 address [4:0] $end
$var reg 32 8 expected [31:0] $end
$upscope $end
$scope task write_register $end
$var reg 5 9 address [4:0] $end
$var reg 32 : data [31:0] $end
$upscope $end
$upscope $end
$enddefinitions $end
$comment Show the parameter values. $end
$dumpall
$end
#0
$dumpvars
bx :
bx 9
bx 8
bx 7
bx 6
bx 5
bx 4
b0 3
b0 2
bx 1
bx 0
b0 /
b0 .
b0 -
bx ,
0+
b0 *
b0 )
1(
b0 '
b0 &
b0 %
0$
bx #
bx "
bx !
$end
#5000
b0 "
b0 0
b0 !
b0 1
b0 #
b0 5
b0 4
b100000 6
1$
#10000
0$
#15000
b100000 6
1$
#20000
b0 8
b0 7
b0 ,
0(
0$
#25000
1$
#30000
0$
#35000
1$
#40000
0$
#45000
1$
#46000
b1 7
b1 ,
#50000
b1 %
b1 -
0$
#55000
b1 4
1$
#60000
0$
#65000
1$
#66000
b10 7
b10 ,
#70000
b10 %
b10 -
0$
#75000
b10 4
1$
#80000
0$
#85000
1$
#86000
b11 7
b11 ,
#90000
b11 %
b11 -
0$
#95000
b11 4
1$
#100000
0$
#105000
1$
#106000
b100 7
b100 ,
#110000
b100 %
b100 -
0$
#115000
b100 4
1$
#120000
0$
#125000
1$
#126000
b101 7
b101 ,
#130000
b101 %
b101 -
0$
#135000
b101 4
1$
#140000
0$
#145000
1$
#146000
b110 7
b110 ,
#150000
b110 %
b110 -
0$
#155000
b110 4
1$
#160000
0$
#165000
1$
#166000
b111 7
b111 ,
#170000
b111 %
b111 -
0$
#175000
b111 4
1$
#180000
0$
#185000
1$
#186000
b1000 7
b1000 ,
#190000
b1000 %
b1000 -
0$
#195000
b1000 4
1$
#200000
0$
#205000
1$
#206000
b1001 7
b1001 ,
#210000
b1001 %
b1001 -
0$
#215000
b1001 4
1$
#220000
0$
#225000
1$
#226000
b1010 7
b1010 ,
#230000
b1010 %
b1010 -
0$
#235000
b1010 4
1$
#240000
0$
#245000
1$
#246000
b1011 7
b1011 ,
#250000
b1011 %
b1011 -
0$
#255000
b1011 4
1$
#260000
0$
#265000
1$
#266000
b1100 7
b1100 ,
#270000
b1100 %
b1100 -
0$
#275000
b1100 4
1$
#280000
0$
#285000
1$
#286000
b1101 7
b1101 ,
#290000
b1101 %
b1101 -
0$
#295000
b1101 4
1$
#300000
0$
#305000
1$
#306000
b1110 7
b1110 ,
#310000
b1110 %
b1110 -
0$
#315000
b1110 4
1$
#320000
0$
#325000
1$
#326000
b1111 7
b1111 ,
#330000
b1111 %
b1111 -
0$
#335000
b1111 4
1$
#340000
0$
#345000
1$
#346000
b10000 7
b10000 ,
#350000
b10000 %
b10000 -
0$
#355000
b10000 4
1$
#360000
0$
#365000
1$
#366000
b10001 7
b10001 ,
#370000
b10001 %
b10001 -
0$
#375000
b10001 4
1$
#380000
0$
#385000
1$
#386000
b10010 7
b10010 ,
#390000
b10010 %
b10010 -
0$
#395000
b10010 4
1$
#400000
0$
#405000
1$
#406000
b10011 7
b10011 ,
#410000
b10011 %
b10011 -
0$
#415000
b10011 4
1$
#420000
0$
#425000
1$
#426000
b10100 7
b10100 ,
#430000
b10100 %
b10100 -
0$
#435000
b10100 4
1$
#440000
0$
#445000
1$
#446000
b10101 7
b10101 ,
#450000
b10101 %
b10101 -
0$
#455000
b10101 4
1$
#460000
0$
#465000
1$
#466000
b10110 7
b10110 ,
#470000
b10110 %
b10110 -
0$
#475000
b10110 4
1$
#480000
0$
#485000
1$
#486000
b10111 7
b10111 ,
#490000
b10111 %
b10111 -
0$
#495000
b10111 4
1$
#500000
0$
#505000
1$
#506000
b11000 7
b11000 ,
#510000
b11000 %
b11000 -
0$
#515000
b11000 4
1$
#520000
0$
#525000
1$
#526000
b11001 7
b11001 ,
#530000
b11001 %
b11001 -
0$
#535000
b11001 4
1$
#540000
0$
#545000
1$
#546000
b11010 7
b11010 ,
#550000
b11010 %
b11010 -
0$
#555000
b11010 4
1$
#560000
0$
#565000
1$
#566000
b11011 7
b11011 ,
#570000
b11011 %
b11011 -
0$
#575000
b11011 4
1$
#580000
0$
#585000
1$
#586000
b11100 7
b11100 ,
#590000
b11100 %
b11100 -
0$
#595000
b11100 4
1$
#600000
0$
#605000
1$
#606000
b11101 7
b11101 ,
#610000
b11101 %
b11101 -
0$
#615000
b11101 4
1$
#620000
0$
#625000
1$
#626000
b11110 7
b11110 ,
#630000
b11110 %
b11110 -
0$
#635000
b11110 4
1$
#640000
0$
#645000
1$
#646000
b11111 7
b11111 ,
#650000
b11111 %
b11111 -
0$
#655000
b11111 4
1$
#660000
0$
#665000
1$
#666000
b10010001101000101011001111000 :
b1 9
b100000 ,
#670000
1+
b10010001101000101011001111000 *
b10010001101000101011001111000 3
b1 )
b1 2
0$
#675000
1$
#680000
b11011110101011011011111011101111 :
b10 9
0+
0$
#685000
1$
#690000
1+
b11011110101011011011111011101111 *
b11011110101011011011111011101111 3
b10 )
b10 2
0$
#695000
1$
#700000
b11011110101011011011111011101111 !
b11011110101011011011111011101111 1
b10010001101000101011001111000 "
b10010001101000101011001111000 0
b10 '
b10 /
b1 &
b1 .
0+
0$
#701000
b11111111111111111111111111111111 :
b0 9
#705000
1$
#710000
1+
b11111111111111111111111111111111 *
b11111111111111111111111111111111 3
b0 )
b0 2
0$
#715000
1$
#720000
b0 "
b0 0
b0 &
b0 .
0+
0$
#721000
b10010001101000101011001111000 "
b10010001101000101011001111000 0
b1 &
b1 .
#722000
b11011110101011011011111011101111 8
b10 7
#725000
1$
#730000
b10 %
b10 -
0$
#735000
b10 4
1$
#740000
0$
#745000
b11011110101011011011111011101111 #
b11011110101011011011111011101111 5
1$
#750000
b10101010101010100101010101010101 *
b10101010101010100101010101010101 3
b1 )
b1 2
0$
#755000
1$
#760000
b10010001101000101011001111000 8
b1 7
0$
#765000
1$
#770000
b1 %
b1 -
0$
#775000
b1 4
1$
#780000
0$
#785000
b10010001101000101011001111000 #
b10010001101000101011001111000 5
1$
